bngmodule/__init__.py
bngmodule/bngmodule.py
bngmodule-1.1.dist-info/METADATA
bngmodule-1.1.dist-info/WHEEL
bngmodule-1.1.dist-info/top_level.txt
bngmodule-1.1.dist-info/RECORD
