Metadata-Version: 2.4
Name: bngmodule
Version: 1.1
Summary: A library for simple sockets and making malware very, very easy
Home-page: https://github.com/salehbngpy
Author: saleh
Requires-Dist: pyttsx3
Requires-Dist: psutil
Dynamic: author
Dynamic: home-page
Dynamic: requires-dist
Dynamic: summary
